devart/bigquery/__init__.py
devart/bigquery/bigquery.cp313-win32.pyd
devart/bigquery/bigquery.pyi
devart/bigquery/BigQuery/Devart.Python.BigQueryEngine.dll
devart/bigquery/BigQuery/sqlite3.dll
devart/bigquery/sqlalchemy/__init__.py
devart_bigquery_connector-1.2.0.dist-info/LICENSE
devart_bigquery_connector-1.2.0.dist-info/METADATA
devart_bigquery_connector-1.2.0.dist-info/WHEEL
devart_bigquery_connector-1.2.0.dist-info/top_level.txt
devart_bigquery_connector-1.2.0.dist-info/RECORD
